Metadata-Version: 1.1
Name: MayReader
Version: 0.0.5
Summary: Reader for maya ascii files
Home-page: UNKNOWN
Author: Milan Mitrovic
Author-email: milan.mitrovic2111@gmail.com
License: MIT
Keywords: Reader
Platform: UNKNOWN
Classifier: Development Status :: 5 - Production/Stable
Classifier: Intended Audience :: Education
Classifier: Operating System :: Microsoft :: Windows :: Windows 10
Classifier: License :: OSI Approved :: MIT License
Classifier: Programming Language :: Python
Classifier: Programming Language :: Python :: 2
Classifier: Programming Language :: Python :: 3
